{"/":{"title":"Rajan Agarwal.","content":"\n![[notes/images/Pasted image 20221017202638.png]]\n\nSeeking serendipity in code, craft \u0026 curiosity.  \nDesigning \u0026 engineering high-scale communities.  \nMeeting wonderful people along the way.  \n  \nCurrently, I'm building ConnexSci to make research accessible and open to funding in the public sector. On the side, I'm working at [JEC Toronto](https://www.jectoronto.org/) (COO), [ChoiceDAO](https://www.choicedao.org/) (Core) and [Cobweb](https://www.cobweb.ca/) (Researcher). Previously, I worked at [Camp Social](https://www.camp.social/) as a Software Engineer Intern.  \n  \nIn my free time, I enjoy writing and spending time outdoors. I'm currently writing a novel, The Platonist, and playing competitive golf, tennis and long distance running.\n\nDo good work. Enjoy the journey.\n\n\u003e _People grow old only by deserting their ideals. Worry, doubt, self-distrust and fear; these are the long years that bow the head and turn the growing spirit back to dust.  Whatever the years, there is in every being the love of wonder, the undaunted challenge of events, the unfailing childlike appetite for what next, and the joy in the game of life._","lastmodified":"2022-10-18T02:15:06.239564516Z","tags":null},"/notes/showcase":{"title":"Showcase","content":"\nWant to see what Quartz can do? Here are some cool community gardens :)\n\n- [Quartz Documentation (this site!)](https://quartz.jzhao.xyz/)\n- [Jacky Zhao's Garden](https://jzhao.xyz/)\n- [Scaling Synthesis - A hypertext research notebook](https://scalingsynthesis.com/)\n- [AWAGMI Intern Notes](https://notes.awagmi.xyz/)\n- [Shihyu's PKM](https://shihyuho.github.io/pkm/)\n- [Chloe's Garden](https://garden.chloeabrasada.online/)\n- [SlRvb's Site](https://slrvb.github.io/Site/)\n- [Course notes for Information Technology Advanced Theory](https://a2itnotes.github.io/quartz/)\n- [Brandon Boswell's Garden](https://brandonkboswell.com)\n- [Siyang's Courtyard](https://siyangsun.github.io/courtyard/)\n- [Data Dictionary 🧠](https://glossary.airbyte.com/)\n- [sspaeti.com's Second Brain](https://brain.sspaeti.com/)\n- [oldwinterの数字花园](https://garden.oldwinter.top/)\n- [SethMB Work](https://sethmb.xyz/)\n\nIf you want to see your own on here, submit a [Pull Request adding yourself to this file](https://github.com/jackyzha0/quartz/blob/hugo/content/notes/showcase.md)!\n","lastmodified":"2022-10-18T02:15:06.239564516Z","tags":null},"/notes/troubleshooting":{"title":"Troubleshooting and FAQ","content":"\nStill having trouble? Here are a list of common questions and problems people encounter when installing Quartz.\n\nWhile you're here, join our [Discord](https://discord.gg/cRFFHYye7t) :)\n\n### Does Quartz have Latex support?\nYes! See [CJK + Latex Support (测试)](notes/CJK%20+%20Latex%20Support%20(测试).md) for a brief demo.\n\n### Can I use \\\u003cObsidian Plugin\\\u003e in Quartz?\nUnless it produces direct Markdown output in the file, no. There currently is no way to bundle plugin code with Quartz.\n\nThe easiest way would be to add your own HTML partial that supports the functionality you are looking for.\n\n### My GitHub pages is just showing the README and not Quartz\nMake sure you set the source to deploy from `master` (and not `hugo`) using `/ (root)`! See more in the [hosting](/notes/hosting) guide\n\n### Some of my pages have 'January 1, 0001' as the last modified date\nThis is a problem caused by `git` treating files as case-insensitive by default and some of your posts probably have capitalized file names. You can turn this off in your Quartz by running this command.\n\n```shell\n# in the root of your Quartz (same folder as config.toml)\ngit config core.ignorecase true\n\n# or globally (not recommended)\ngit config --global core.ignorecase true\n```\n\n### Can I publish only a subset of my pages?\nYes! Quartz makes selective publishing really easy. Heres a guide on [excluding pages from being published](notes/ignore%20notes.md).\n\n### Can I host this myself and not on GitHub Pages?\nYes! All built files can be found under `/public` in the `master` branch. More details under [hosting](notes/hosting.md).\n\n### `command not found: hugo-obsidian`\nMake sure you set your `GOPATH` correctly! This will allow your terminal to correctly recognize `hugo-obsidian` as an executable.\n\n```shell\n# Add the following 2 lines to your ~/.bash_profile\nexport GOPATH=/Users/$USER/go\nexport PATH=$GOPATH/bin:$PATH\n\n# In your current terminal, to reload the session\nsource ~/.bash_profile\n```\n\n### How come my notes aren't being rendered?\nYou probably forgot to include front matter in your Markdown files. You can either setup [Obsidian](notes/obsidian.md) to do this for you or you need to manually define it. More details in [the 'how to edit' guide](notes/editing.md).\n\n### My custom domain isn't working!\nWalk through the steps in [the hosting guide](notes/hosting.md) again. Make sure you wait 30 min to 1 hour for changes to take effect.\n\n### How do I setup Google Analytics?\nYou can edit it in `config.toml` and either use a V3 (UA-) or V4 (G-) tag.\n\n### How do I change the content on the home page?\nTo edit the main home page, open `/content/_index.md`.\n\n### How do I change the colours?\nYou can change the theme by editing `assets/custom.scss`. More details on customization and themeing can be found in the [customization guide](notes/config.md).\n\n### How do I add images?\nYou can put images anywhere in the `/content` folder.\n\n```markdown\nExample image (source is in content/notes/images/example.png)\n![Example Image](/content/notes/images/example.png)\n```\n\n### My Interactive Graph and Backlinks aren't up to date\nBy default, the `linkIndex.json` (which Quartz needs to generate the Interactive Graph and Backlinks) are not regenerated locally. To set that up, see the guide on [local editing](notes/editing.md)\n\n### Can I use React/Vue/some other framework?\nNot out of the box. You could probably make it work by editing `/layouts/_default/single.html` but that's not what Quartz is designed to work with. 99% of things you are trying to do with those frameworks you can accomplish perfectly fine using just vanilla HTML/CSS/JS.\n\n## Still Stuck?\nQuartz isn't perfect! If you're still having troubles, file an issue in the GitHub repo with as much information as you can reasonably provide. Alternatively, you can message me on [Twitter](https://twitter.com/_jzhao) and I'll try to get back to you as soon as I can.\n\n🐛 [Submit an Issue](https://github.com/jackyzha0/quartz/issues)","lastmodified":"2022-10-18T02:15:06.239564516Z","tags":null},"/notes/updating":{"title":"Updating","content":"\nHaven't updated Quartz in a while and want all the cool new optimizations? On Unix/Mac systems you can run the following command for a one-line update! This command will show you a log summary of all commits since you last updated, press `q` to acknowledge this. Then, it will show you each change in turn and press `y` to accept the patch or `n` to reject it. Usually you should press `y` for most of these unless it conflicts with existing changes you've made! \n\n```shell\nmake update\n```\n\nOr, if you don't want the interactive parts and just want to force update your local garden (this assumed that you are okay with some of your personalizations been overriden!)\n\n```shell\nmake update-force\n```\n\nOr, manually checkout the changes yourself.\n\n\u003e [!warning] Warning!\n\u003e\n\u003e If you customized the files in `data/`, or anything inside `layouts/`, your customization may be overwritten!\n\u003e Make sure you have a copy of these changes if you don't want to lose them.\n\n\n```shell\n# add Quartz as a remote host\ngit remote add upstream git@github.com:jackyzha0/quartz.git\n\n# index and fetch changes\ngit fetch upstream\ngit checkout -p upstream/hugo -- layouts .github Makefile assets/js assets/styles/base.scss assets/styles/darkmode.scss config.toml data \n```\n","lastmodified":"2022-10-18T02:15:06.239564516Z","tags":null}}